LICENSE
MANIFEST.in
README.md
setup.py
wxdb/__init__.py
wxdb/events.py
wxdb/listener.py
wxdb/logger.py
wxdb/utils.py
wxdb/wechat-dump-rs.exe
wxdb.egg-info/PKG-INFO
wxdb.egg-info/SOURCES.txt
wxdb.egg-info/dependency_links.txt
wxdb.egg-info/requires.txt
wxdb.egg-info/top_level.txt
wxdb/v3/__init__.py