Metadata-Version: 2.2
Name: wxdb
Version: 0.0.9
Summary: wechat database manager.
Home-page: https://github.com/miloira/wxdb
Author: Msky
Author-email: 690126048@qq.com
License: MIT
Classifier: License :: OSI Approved :: MIT License
Classifier: Programming Language :: Python
Classifier: Programming Language :: Python :: 3
Classifier: Programming Language :: Python :: 3.8
Classifier: Programming Language :: Python :: Implementation :: CPython
Classifier: Programming Language :: Python :: Implementation :: PyPy
Requires-Python: >=3.8.0
License-File: LICENSE
Requires-Dist: blackboxprotobuf
Requires-Dist: loguru
Requires-Dist: lz4
Requires-Dist: pycryptodome
Requires-Dist: pyee
Requires-Dist: sqlcipher3-wheels
Requires-Dist: xmltodict
Dynamic: author
Dynamic: author-email
Dynamic: classifier
Dynamic: description
Dynamic: description-content-type
Dynamic: home-page
Dynamic: license
Dynamic: requires-dist
Dynamic: requires-python
Dynamic: summary
